{
    "account_supported": false,
    "api": "bibliotheca",
    "city": "Engen",
    "country": "Deutschland",
    "data": {
        "accounttable": null,
        "baseurl": "http://www.bibliotheken.bw-online.de/wwwopac-engen",
        "copiestable": {
            "barcode": -1,
            "branch": 0,
            "department": -1,
            "location": 1,
            "reservations": -1,
            "returndate": 4,
            "status": 3
        },
        "reservationtable": null
    },
    "geo": [
        47.854144,
        8.7737404
    ],
    "information": "http://www.engen.de/servlet/PB/menu/1254107/index.html",
    "state": "Baden-W\u00fcrttemberg",
    "title": "Stadtbibliothek"
}
