{
    "account_supported": true,
    "api": "adis",
    "city": "Grevenbroich",
    "country": "Deutschland",
    "data": {
        "baseurl": "https://webopac.itk-rheinland.de/aDISWeb/app",
        "startparams": "service=direct/0/Home/$DirectLink&sp=S127.0.0.1:23042"
    },
    "geo": [
        51.0902094,
        6.585863000000001
    ],
    "information": "http://www.grevenbroich.de/C1257138004C5579/html/C62D4062F710B7C9C125716F0037EFA2?opendocument&nid1=55151",
    "state": "Nordrhein-Westfalen",
    "title": "Stadtbibliothek"
}