{
    "account_supported": true,
    "api": "bibliotheca",
    "city": "Stendal",
    "country": "Deutschland",
    "data": {
        "accounttable": {
            "author": 1,
            "barcode": 0,
            "homebranch": 4,
            "lendingbranch": 4,
            "prolongurl": 5,
            "returndate": 3,
            "title": 2
        },
        "baseurl": "http://katalog.stadtbibliothek-stendal.de/webopac",
        "copiestable": {
            "branch": 0,
            "department": 3,
            "location": 2,
            "returndate": 6,
            "status": 5
        },
        "mediatypes": {
            "B.gif": "BOOK",
            "BK.gif": "BOOK",
            "BS.gif": "BOOK",
            "CD.gif": "CD",
            "CDH.gif": "AUDIOBOOK",
            "DVDBR.gif": "BLURAY",
            "DVDK.gif": "DVD",
            "ROM.gif": "CD_SOFTWARE",
            "Zt.gif": "NEWSPAPER",
            "cdhk.gif": "CD",
            "cdk.gif": "CD",
            "dm.gif": "SCORE_MUSIC",
            "dvd.gif": "DVD",
            "lk.gif": "MAP",
            "mk.gif": "PACKAGE",
            "mkk.gif": "PACKAGE",
            "romk.gif": "CD_SOFTWARE",
            "x.gif": "UNKNOWN",
            "zss.gif": "MAGAZINE",
            "zssk.gif": "MAGAZINE"
        },
        "reservationtable": {
            "author": 0,
            "branch": 2,
            "cancelurl": 3,
            "title": 1
        }
    },
    "geo": [
        52.6041444,
        11.8517729
    ],
    "information": "http://bibliothek.stendal.de/de/startseite.html",
    "state": "Sachsen-Anhalt",
    "title": "Stadtbibliothek"
}