{
    "api": "bibliotheca", 
    "city": "Ebhausen", 
    "country": "Deutschland", 
    "data": {
        "accounttable": {
            "author": 0, 
            "prolongurl": 3, 
            "returndate": 2, 
            "title": 1
        }, 
        "baseurl": "http://www.bibliotheken.bw-online.de/wwwopac-ebhausen", 
        "copiestable": {
            "branch": 4, 
            "location": 2, 
            "returndate": 1, 
            "status": 0
        }, 
        "information": "http://www.bibliotheken.bw-online.de/read-ebhausen/info.html", 
        "mediatypes": {
            "DVDkl.gif": "DVD", 
            "cdkl.gif": "AUDIOBOOK", 
            "mCasetteS.gif": "AUDIO_CASSETTE", 
            "mComput1S.gif": "CD_SOFTWARE", 
            "monooS.gif": "BOOK", 
            "spieleS.gif": "BOARDGAME", 
            "zeitschrift.gif": "MAGAZINE"
        }, 
        "reservationtable": {
            "author": 0, 
            "availability": 2, 
            "cancelurl": 3, 
            "title": 1
        }
    }, 
    "geo": [
        48.5833057, 
        8.6814596
    ], 
    "state": "Baden-W\u00fcrttemberg", 
    "support": "Katalogsuche und Konto", 
    "title": "Mediathek"
}