{
    "api": "bibliotheca", 
    "city": "Kulmbach", 
    "data": {
        "accounttable": [
            -1, 
            0, 
            1, 
            2, 
            -1, 
            -1, 
            -1, 
            3
        ], 
        "baseurl": "http://opac.buecherei-kulmbach.de/wwwopac", 
        "copiestable": [
            -1, 
            -1, 
            3, 
            2, 
            0, 
            1, 
            -1
        ], 
        "information": "http://www.kulmbach.de/xist4c/web/Anschrift/Teledaten/Oeffnungszeiten_id_981_.htm", 
        "mediatypes": {
            "EM_klein.jpg": "EBOOK", 
            "mDVDS.gif": "DVD", 
            "mFilmS.gif": "MOVIE"
        }, 
        "reservationtable": [
            0, 
            1, 
            2, 
            -1, 
            3, 
            -1
        ]
    }, 
    "geo": [
        50.1039282, 
        11.4448178
    ], 
    "group": "Bayern", 
    "support": "Katalogsuche und Konto", 
    "title": "B\u00fccherei am Stadtpark"
}
