{
    "api": "bibliotheca", 
    "city": "Magdeburg", 
    "data": {
        "accounttable": {
            "author": 1, 
            "barcode": 0, 
            "homebranch": 4, 
            "lendingbranch": 4, 
            "prolongurl": 5, 
            "returndate": 3, 
            "status": -1, 
            "title": 2
        }, 
        "baseurl": "http://auskunft.stadtbibliothek.magdeburg.de/webopac", 
        "copiestable": {
            "barcode": -1, 
            "branch": 0, 
            "department": -1, 
            "location": 2, 
            "reservations": -1, 
            "returndate": 5, 
            "status": 4
        }, 
        "information": "http://www.magdeburg-stadtbibliothek.de/texte/seite.php?id=98014", 
        "mediatypes": {
            "B.gif": "BOOK", 
            "BK.gif": "BOOK", 
            "BS.gif": "BOOK", 
            "CD.gif": "CD", 
            "CDH.gif": "AUDIOBOOK", 
            "DVDBR.gif": "BLURAY", 
            "DVDK.gif": "DVD", 
            "ROM.gif": "CD_SOFTWARE", 
            "Zt.gif": "NEWSPAPER", 
            "blue-ray_Kind.gif": "BLURAY", 
            "cdhk.gif": "AUDIOBOOK", 
            "cdk.gif": "CD", 
            "dm.gif": "SCORE_MUSIC", 
            "dvd.gif": "DVD", 
            "em.gif": "EBOOK", 
            "lk.gif": "MAP", 
            "mk.gif": "PACKAGE", 
            "mkk.gif": "PACKAGE", 
            "romk.gif": "CD_SOFTWARE", 
            "x.gif": "UNKNOWN", 
            "zss.gif": "MAGAZINE", 
            "zssk.gif": "MAGAZINE"
        }, 
        "reservationtable": {
            "author": 0, 
            "availability": -1, 
            "branch": 2, 
            "cancelurl": 3, 
            "expirationdate": null, 
            "title": 1
        }
    }, 
    "geo": [
        52.130807, 
        11.628878
    ], 
    "group": "Sachsen-Anhalt", 
    "support": "Katalogsuche und Konto", 
    "title": "Stadtbibliothek"
}