{
    "api": "biber1992", 
    "city": "N\u00fcrtingen", 
    "data": {
        "accounttable": {
            "author": 8, 
            "barcode": 4, 
            "homebranch": -1, 
            "lendingbranch": -1, 
            "prolongurl": 4, 
            "returndate": 3, 
            "status": 6, 
            "title": 8
        }, 
        "baseurl": "http://biber-nuert.kdrs.de:8182", 
        "information": "http://www.nuertingen.de/?id=260",
        "mediatypes": {
            "1": "BOOK", 
            "2": "BOOK",
			"10": "MAGAZINE",
			"3": "BOOK",
			"6": "CD",
			"4": "MOVIE",
            "11": "MOVIE", 
            "5": "CD", 
            "9": "BOARDGAME", 
            "4": "GAME_CONSOLE_WII", 
            "30": "EBOOK", 
            "6": "CD", 
            "8": "BOOK"
        }, 
        "opacdir": "opax", 
        "searchtable": [
            2, 
            3, 
            4
        ]
    }, 
    "geo": [
        48.624421, 
        9.3469069
    ], 
    "group": "Baden-W\u00fcrttemberg", 
    "support": "Katalogsuche und Konto", 
    "title": "Stadtb\u00fccherei"
}
