{
    "api": "pica", 
    "city": "Stralsund", 
    "country": "Deutschland", 
    "data": {
        "accountSupported": true, 
        "baseurl": "http://opac.ub.uni-greifswald.de/", 
        "db": "2", 
        "httpsbaseurl": "https://opac.ub.uni-greifswald.de/", 
        "information": "http://www.fh-stralsund.de/fh_stralsund/powerslave,id,765,nodeid,.html"
    }, 
    "geo": [
        54.2994048, 
        13.0877143
    ], 
    "state": "Mecklenburg-Vorpommern", 
    "support": "Katalogsuche und Konto", 
    "title": "Hochschulbibliothek"
}