{
    "api": "biber1992", 
    "city": "W\u00fcrzburg", 
    "data": {
        "baseurl": "http://217.7.118.50", 
        "copiestable": [
            3, 
            1, 
            2, 
            -1, 
            4, 
            -1, 
            -1
        ], 
        "information": "http://www.wuerzburg.de/de/buerger/stadtbuecherei/index.html", 
        "mediatypes": {
            "1": "BOOK", 
            "10": "MAP", 
            "11": "DVD", 
            "19": "BOOK", 
            "2": "MAGAZINE", 
            "24": "BLURAY", 
            "3": "CD_SOFTWARE", 
            "30": "EBOOK", 
            "6": "CD_MUSIC", 
            "8": "SCORE_MUSIC", 
            "9": "BOARDGAME"
        }, 
        "opacdir": "opax", 
        "searchtable": [
            2, 
            3, 
            4, 
            5
        ]
    }, 
    "geo": [
        49.7915953, 
        9.953571499999999
    ], 
    "group": "Bayern", 
    "support": "Katalogsuche", 
    "title": "Stadtb\u00fccherei"
}